<?xml version="1.0" encoding="UTF-8"?>
<config>
    <nav>
        <usuario>
            <label>Usuário</label>
            <controller>usuario</controller>
            <action>index</action>
            <pages>
                <usuarioCreate>
                    <label>Cadastrar </label>
                    <controller>usuario</controller>
                    <action>create</action>
                </usuarioCreate>
                <usuarioUpdate>
                    <label>Alterar </label>
                    <controller>usuario</controller>
                    <action>update</action>
                </usuarioUpdate>
            </pages>
        </usuario>
        <cliente>
            <label>Cliente</label>
            <controller>cliente</controller>
            <action>index</action>
            <pages>
                <clienteCreate>
                    <label>Cadastrar </label>
                    <controller>cliente</controller>
                    <action>create</action>
                </clienteCreate>
                <clienteUpdate>
                    <label>Alterar </label>
                    <controller>cliente</controller>
                    <action>update</action>
                </clienteUpdate>
            </pages>
        </cliente>
        <produto>
            <label>Produto</label>
            <controller>produtos</controller>
            <action>index</action>
            <pages>
                <produtoCreate>
                    <label>Cadastrar </label>
                    <controller>produtos</controller>
                    <action>create</action>
                </produtoCreate>
                <produtoUpdate>
                    <label>Alterar </label>
                    <controller>produtos</controller>
                    <action>update</action>
                </produtoUpdate>
            </pages>
        </produto>
        <fornecedor>
            <label>Fornecedor</label>
            <controller>fornecedor</controller>
            <action>index</action>
            <pages>
                <fornecedorCreate>
                    <label>Cadastrar</label>
                    <controller>fornecedor</controller>
                    <action>create</action>
                </fornecedorCreate>
                <fornecedorUpdate>
                    <label>Alterar </label>
                    <controller>fornecedor</controller>
                    <action>update</action>
                </fornecedorUpdate>
            </pages>
        </fornecedor>
        <venda>
            <label>Venda</label>
            <controller>venda</controller>
            <action>index</action>
            <pages>
                <vendaCreate>
                    <label>Efetuar Venda</label>
                    <controller>venda</controller>
                    <action>create</action>
                </vendaCreate>
            </pages>
        </venda>
        <compra>
            <label>Compra</label>
            <controller>compra</controller>
            <action>index</action>
            <pages>
                <vendaCreate>
                    <label>Efetuar Compra</label>
                    <controller>compra</controller>
                    <action>create</action>
                </vendaCreate>
            </pages>
        </compra>
        <ContasReceber>
            <label>Contas Receber</label>
            <controller>ContasReceber</controller>
            <action>index</action>
            <pages>
                <ContasReceber>
                    <label>Faturar Venda</label>
                    <controller>ContasReceber</controller>
                    <action>create</action>
                </ContasReceber>
            </pages>
        </ContasReceber>
        <ContasPagar>
            <label>Contas Pagar</label>
            <controller>ContasPagar</controller>
            <action>index</action>
            <pages>
                <ContasPagar>
                    <label>Faturar Compra</label>
                    <controller>ContasPagar</controller>
                    <action>create</action>
                </ContasPagar>
            </pages>
        </ContasPagar>
        <relatorio>
            <label>Relatorio</label>
            <controller>relatorio</controller>
            <action>index</action>
            <pages>
                <relatorio>
                    <label>Venda Por Data</label>
                    <controller>relatorio</controller>
                    <action>vendapordata</action>
                </relatorio>
            </pages>
        </relatorio>
    </nav>
</config>
    

